PathPlanning/node.v
module node(add, o0, o1, o2, o3);
	input [4:0]add;
	output reg [0:6]o0, o1, o2, o3;
	
	reg [0:6]m[0:25][0:3];
	
	initial begin
	m[0][0] = {2'd3, 5'd1};
	m[0][1] = {2'd3, 5'd30};
	m[0][2] = {2'd3, 5'd30};
	m[0][3] = {2'd3, 5'd30};

	m[1][0] = {2'd3, 5'd0};
	m[1][1] = {2'd3, 5'd2};
	m[1][2] = {2'd3, 5'd13};
	m[1][3] = {2'd3, 5'd30};

	m[2][0] = {2'd3, 5'd1};
	m[2][1] = {2'd1, 5'd3};
	m[2][2] = {2'd3, 5'd5};
	m[2][3] = {2'd3, 5'd30};

	m[3][0] = {2'd1, 5'd2};
	m[3][1] = {2'd3, 5'd30};
	m[3][2] = {2'd3, 5'd30};
	m[3][3] = {2'd3, 5'd30};

	m[4][0] = {2'd3, 5'd6};
	m[4][1] = {2'd3, 5'd30};
	m[4][2] = {2'd3, 5'd30};
	m[4][3] = {2'd3, 5'd30};

	m[5][0] = {2'd3, 5'd2};
	m[5][1] = {2'd2, 5'd9};
	m[5][2] = {2'd1, 5'd6};
	m[5][3] = {2'd3, 5'd30};

	m[6][0] = {2'd3, 5'd4};
	m[6][1] = {2'd3, 5'd16};
	m[6][2] = {2'd1, 5'd5};
	m[6][3] = {2'd3, 5'd30};

	m[7][0] = {2'd2, 5'd12};
	m[7][1] = {2'd3, 5'd30};
	m[7][2] = {2'd3, 5'd30};
	m[7][3] = {2'd3, 5'd30};

	m[8][0] = {2'd1, 5'd9};
	m[8][1] = {2'd3, 5'd30};
	m[8][2] = {2'd3, 5'd30};
	m[8][3] = {2'd3, 5'd30};

	m[9][0] = {2'd1, 5'd8};
	m[9][1] = {2'd1, 5'd15};
	m[9][2] = {2'd2, 5'd5};
	m[9][3] = {2'd3, 5'd30};

	m[10][0] = {2'd2, 5'd16};
	m[10][1] = {2'd3, 5'd30};
	m[10][2] = {2'd3, 5'd30};
	m[10][3] = {2'd3, 5'd30};

	m[11][0] = {2'd3, 5'd12};
	m[11][1] = {2'd3, 5'd30};
	m[11][2] = {2'd3, 5'd30};
	m[11][3] = {2'd3, 5'd30};

	m[12][0] = {2'd3, 5'd11};
	m[12][1] = {2'd2, 5'd7};
	m[12][2] = {2'd1, 5'd13};
	m[12][3] = {2'd3, 5'd17};

	m[13][0] = {2'd1, 5'd12};
	m[13][1] = {2'd2, 5'd18};
	m[13][2] = {2'd3, 5'd1};
	m[13][3] = {2'd3, 5'd30};

	m[14][0] = {2'd1, 5'd15};
	m[14][1] = {2'd3, 5'd30};
	m[14][2] = {2'd3, 5'd30};
	m[14][3] = {2'd3, 5'd30};

	m[15][0] = {2'd1, 5'd14};
	m[15][1] = {2'd1, 5'd9};
	m[15][2] = {2'd1, 5'd22};
	m[15][3] = {2'd3, 5'd30};

	m[16][0] = {2'd2, 5'd10};
	m[16][1] = {2'd2, 5'd23};
	m[16][2] = {2'd3, 5'd6};
	m[16][3] = {2'd3, 5'd30};

	m[17][0] = {2'd3, 5'd12};
	m[17][1] = {2'd3, 5'd30};
	m[17][2] = {2'd3, 5'd30};
	m[17][3] = {2'd3, 5'd30};

	m[18][0] = {2'd1, 5'd19};
	m[18][1] = {2'd1, 5'd20};
	m[18][2] = {2'd2, 5'd13};
	m[18][3] = {2'd3, 5'd30};

	m[19][0] = {2'd1, 5'd18};
	m[19][1] = {2'd3, 5'd30};
	m[19][2] = {2'd3, 5'd30};
	m[19][3] = {2'd3, 5'd30};

	m[20][0] = {2'd1, 5'd18};
	m[20][1] = {2'd1, 5'd21};
	m[20][2] = {2'd2, 5'd22};
	m[20][3] = {2'd3, 5'd30};

	m[21][0] = {2'd1, 5'd20};
	m[21][1] = {2'd3, 5'd30};
	m[21][2] = {2'd3, 5'd30};
	m[21][3] = {2'd3, 5'd30};

	m[22][0] = {2'd1, 5'd23};
	m[22][1] = {2'd1, 5'd15};
	m[22][2] = {2'd2, 5'd20};
	m[22][3] = {2'd3, 5'd25};

	m[23][0] = {2'd1, 5'd22};
	m[23][1] = {2'd2, 5'd24};
	m[23][2] = {2'd2, 5'd16};
	m[23][3] = {2'd3, 5'd30};

	m[24][0] = {2'd2, 5'd23};
	m[24][1] = {2'd3, 5'd30};
	m[24][2] = {2'd3, 5'd30};
	m[24][3] = {2'd3, 5'd30};

	m[25][0] = {2'd3, 5'd22};
	m[25][1] = {2'd3, 5'd30};
	m[25][2] = {2'd3, 5'd30};
	m[25][3] = {2'd3, 5'd30};
	
	end
	always @(add)begin
		o0 = m[add][0];
		o1 = m[add][1];
		o2 = m[add][2];
		o3 = m[add][3];
	end
endmodule

PathPlanning/path.v
`include "node.v"
module path(clk, st_node, end_node, prevNode, f);
	input clk;
	input [0:4]st_node, end_node;
	//output [0:49]pth;
	
	reg [0:4]currentNode;
	wire [0:3][0:4]nextNode;
	wire [0:3][0:1]addLength;
	
	node n(currentNode, {addLength[0], nextNode[0]}, {addLength[1],nextNode[1]}, {addLength[2],nextNode[2]}, {addLength[3],nextNode[3]});
	
	reg found = 0;
	reg [0:25]explored;
	reg [0:25][0:4]exploredLength;
	output reg f;
	output reg [0:25][0:4]prevNode;
	
	reg [0:1023]que;
	
	always @(st_node, end_node) begin
		z = 0;
		found = 0;
		f = 0;
		i = 0;
		x = 0;
	end
	
	integer i=0,j,k,x=0;
	reg [0:4]nn;	
	always @(posedge clk) begin
	if(found == 0) begin
		f = 1'b0;
		if(currentNode < 26) begin
		if(explored[currentNode] == 0) begin
		
		for(j=0; j<4; j=j+1) begin
			for(k=0; k<5; k=k+1) begin
				nn=nextNode[j];
				que[20*x + 5*j + k] = nn[k];
			end
		end
		x = x + 1;
		explored[currentNode] = 1'b1;
			for(j=0; j<4; j=j+1) begin
				nn=nextNode[j];
				if(nn < 26) begin
					if(exploredLength[currentNode]+addLength[j] < exploredLength[nn]) begin
						exploredLength[nn] = exploredLength[currentNode]+addLength[j];
						prevNode[nn] = currentNode;
						if(nn == end_node)
							found = 1'b1;
					end
				end
			end
		end		
		end
		i=i+1;
	end
	else
		f=1'b1;
	end
	
	integer z=0;
	always @(negedge clk) begin
		for(j=0; j<5; j=j+1) begin
			currentNode[j] = que[5*(i-1) + j];
		end
		if(z == 0) begin
		for(j=0; j<26; j=j+1) begin
			explored[j] = 1'b0;
			exploredLength[j] = 5'b11111;
		end
		currentNode = st_node;
		exploredLength[st_node] = 5'b00000;
		z=1;
		end
	end	
endmodule

PathPlanning/nodeList.v
`include "path.v"
module pathDecode(clk, st_node, end_node, nodeList);
	input clk;
	input [0:4] st_node, end_node;
	output reg [0:99]nodeList;
	
	wire [0:25][0:4]o;
	wire f;
	reg ff = 0;
	
	path p(clk, st_node, end_node, o, f);
	
	integer i=1, j;
	reg [0:4] crnt, prev;
	
	always @(negedge f) ff = 0;
	
	always @(posedge f) begin
		crnt = end_node;
		prev = end_node;
		{nodeList} = {nodeList, end_node};
	end
	
	always @(posedge clk) begin
	if(ff == 0) begin
		if(f == 1) begin
			prev = o[crnt];
			{nodeList} = {nodeList, prev};
			if(prev == st_node)
				ff = 1;
		end
		else begin
			crnt = end_node;
			prev = end_node;
			i=0;
		end
	end
	end
	always @(negedge clk) begin
	if(ff == 0) begin
		if(f == 1)
			crnt = prev;
		else
			prev = end_node;
	end
	end
endmodule

PathPlanning/tb.v
`include "nodeList.v"
module tb;
	reg clk=0;
	reg [0:4]st_node = 5'd3;
	reg [0:4]end_node = 5'd25;
	wire [0:99]o;
	always #2 clk = ~clk;
	
	pathDecode n(clk, st_node, end_node, o); 
	
	integer i;
	initial begin
		$dumpfile("tb.vcd");
		$dumpvars;
		$monitor("%t : %d_%d_%d_%d_%d_%d_%d_%d_%d_%d_%d_%d_%d_%d_%d_%d_%d_%d_%d_%d", $time,o[95:99],o[90:94],o[85:89],o[80:84],o[75:79],o[70:74],o[65:69],o[60:64],o[55:59],o[50:54],o[45:49],o[40:44],o[35:39],o[30:34],o[25:29],o[20:24],o[15:19],o[10:14],o[5:9],o[0:4]);
		#500;
		$finish;
	end	
endmodule

PathPlanning/tb.vcd
$date
	Sat Jun 29 18:37:08 2024
$end
$version
	Icarus Verilog
$end
$timescale
	1s
$end
$scope module tb $end
$var wire 100 ! o [0:99] $end
$var reg 1 " clk $end
$var reg 5 # end_node [0:4] $end
$var reg 5 $ st_node [0:4] $end
$scope module n $end
$var wire 1 " clk $end
$var wire 5 % end_node [0:4] $end
$var wire 5 & st_node [0:4] $end
$var wire 130 ' o [129:0] $end
$var wire 1 ( f $end
$var reg 5 ) crnt [0:4] $end
$var reg 1 * ff $end
$var reg 100 + nodeList [0:99] $end
$var reg 5 , prev [0:4] $end
$var integer 32 - i [31:0] $end
$scope module p $end
$var wire 1 " clk $end
$var wire 5 . end_node [0:4] $end
$var wire 5 / st_node [0:4] $end
$var wire 20 0 nextNode [19:0] $end
$var wire 8 1 addLength [7:0] $end
$var reg 5 2 currentNode [0:4] $end
$var reg 26 3 explored [0:25] $end
$var reg 130 4 exploredLength [129:0] $end
$var reg 1 ( f $end
$var reg 1 5 found $end
$var reg 5 6 nn [0:4] $end
$var reg 130 7 prevNode [129:0] $end
$var reg 1024 8 que [0:1023] $end
$var integer 32 9 i [31:0] $end
$var integer 32 : j [31:0] $end
$var integer 32 ; k [31:0] $end
$var integer 32 < x [31:0] $end
$var integer 32 = z [31:0] $end
$scope module n $end
$var wire 5 > add [4:0] $end
$var reg 7 ? o0 [0:6] $end
$var reg 7 @ o1 [0:6] $end
$var reg 7 A o2 [0:6] $end
$var reg 7 B o3 [0:6] $end
$upscope $end
$upscope $end
$upscope $end
$upscope $end
$enddefinitions $end
$comment Show the parameter values. $end
$dumpall
$end
#0
$dumpvars
b1111110 B
b1111110 A
b1111110 @
b100010 ?
b11 >
b0 =
b0 <
bx ;
b11010 :
b0 9
bx 8
bx 7
bx 6
05
b1111111111111110000011111111111111111111111111111111111111111111111111111111111111111111111111111111111111111111111111111111111111 4
b0 3
b11 2
b1111111 1
b10111101111011110 0
b11 /
b11001 .
b1 -
b11001 ,
bx +
0*
bx )
0(
bx '
b11 &
b11001 %
b11 $
b11001 #
0"
bx !
$end
#2
b1 9
bx00011xxxxxxxxxxxxxxxxxxxxxxxxxxxxxxxxxxxxxxxxxxxxxxxxxxxxxxxxxxxxxxxxxxxxxxxxxxxxxxxxxxxxxxxxxxxxxxxxxxxxxxxxxxxxxxxxxxx '
bx00011xxxxxxxxxxxxxxxxxxxxxxxxxxxxxxxxxxxxxxxxxxxxxxxxxxxxxxxxxxxxxxxxxxxxxxxxxxxxxxxxxxxxxxxxxxxxxxxxxxxxxxxxxxxxxxxxxxx 7
b1111111111000010000011111111111111111111111111111111111111111111111111111111111111111111111111111111111111111111111111111111111111 4
b10000000000000000000000 3
b1 <
b10111101111011110xxxxxxxxxxxxxxxxxxxxxxxxxxxxxxxxxxxxxxxxxxxxxxxxxxxxxxxxxxxxxxxxxxxxxxxxxxxxxxxxxxxxxxxxxxxxxxxxxxxxxxxxxxxxxxxxxxxxxxxxxxxxxxxxxxxxxxxxxxxxxxxxxxxxxxxxxxxxxxxxxxxxxxxxxxxxxxxxxxxxxxxxxxxxxxxxxxxxxxxxxxxxxxxxxxxxxxxxxxxxxxxxxxxxxxxxxxxxxxxxxxxxxxxxxxxxxxxxxxxxxxxxxxxxxxxxxxxxxxxxxxxxxxxxxxxxxxxxxxxxxxxxxxxxxxxxxxxxxxxxxxxxxxxxxxxxxxxxxxxxxxxxxxxxxxxxxxxxxxxxxxxxxxxxxxxxxxxxxxxxxxxxxxxxxxxxxxxxxxxxxxxxxxxxxxxxxxxxxxxxxxxxxxxxxxxxxxxxxxxxxxxxxxxxxxxxxxxxxxxxxxxxxxxxxxxxxxxxxxxxxxxxxxxxxxxxxxxxxxxxxxxxxxxxxxxxxxxxxxxxxxxxxxxxxxxxxxxxxxxxxxxxxxxxxxxxxxxxxxxxxxxxxxxxxxxxxxxxxxxxxxxxxxxxxxxxxxxxxxxxxxxxxxxxxxxxxxxxxxxxxxxxxxxxxxxxxxxxxxxxxxxxxxxxxxxxxxxxxxxxxxxxxxxxxxxxxxxxxxxxxxxxxxxxxxxxxxxxxxxxxxxxxxxxxxxxxxxxxxxxxxxxxxxxxxxxxxxxxxxxxxxxxxxxxxxxxxxxxxxxxxxxxxxxxxxxxxxxxxxxxxxxxxxxxxxxxxxxxxxxxxxxxxxxxxxxxxxxxxxxxxxxxxxxxxxxxxxxxxxxxxxxxxxxxxxxxxxxxxxxxxxxxxxxxxxxxxxxxxxxxxxxxxxxxxxxxxxxxxxxxxxxxxxxxxxxxxxxxxxxxxxxxxxxxxxxxxxxxxxxxxxxxxxxxxxxxxxxxxxxxxxxxxxxxxxxxxxxxxxxxxxxxxxxxxxxxxxxxxxxxxxx 8
b11110 6
b101 ;
b100 :
b0 -
b11001 )
1"
#4
b1 =
b0 3
b1111111111111110000011111111111111111111111111111111111111111111111111111111111111111111111111111111111111111111111111111111111111 4
b11 2
b11 >
b11010 :
0"
#6
b10 9
b1111111111000010000011111111111111111111111111111111111111111111111111111111111111111111111111111111111111111111111111111111111111 4
b10000000000000000000000 3
b10 <
b1011110111101111000010111101111011110xxxxxxxxxxxxxxxxxxxxxxxxxxxxxxxxxxxxxxxxxxxxxxxxxxxxxxxxxxxxxxxxxxxxxxxxxxxxxxxxxxxxxxxxxxxxxxxxxxxxxxxxxxxxxxxxxxxxxxxxxxxxxxxxxxxxxxxxxxxxxxxxxxxxxxxxxxxxxxxxxxxxxxxxxxxxxxxxxxxxxxxxxxxxxxxxxxxxxxxxxxxxxxxxxxxxxxxxxxxxxxxxxxxxxxxxxxxxxxxxxxxxxxxxxxxxxxxxxxxxxxxxxxxxxxxxxxxxxxxxxxxxxxxxxxxxxxxxxxxxxxxxxxxxxxxxxxxxxxxxxxxxxxxxxxxxxxxxxxxxxxxxxxxxxxxxxxxxxxxxxxxxxxxxxxxxxxxxxxxxxxxxxxxxxxxxxxxxxxxxxxxxxxxxxxxxxxxxxxxxxxxxxxxxxxxxxxxxxxxxxxxxxxxxxxxxxxxxxxxxxxxxxxxxxxxxxxxxxxxxxxxxxxxxxxxxxxxxxxxxxxxxxxxxxxxxxxxxxxxxxxxxxxxxxxxxxxxxxxxxxxxxxxxxxxxxxxxxxxxxxxxxxxxxxxxxxxxxxxxxxxxxxxxxxxxxxxxxxxxxxxxxxxxxxxxxxxxxxxxxxxxxxxxxxxxxxxxxxxxxxxxxxxxxxxxxxxxxxxxxxxxxxxxxxxxxxxxxxxxxxxxxxxxxxxxxxxxxxxxxxxxxxxxxxxxxxxxxxxxxxxxxxxxxxxxxxxxxxxxxxxxxxxxxxxxxxxxxxxxxxxxxxxxxxxxxxxxxxxxxxxxxxxxxxxxxxxxxxxxxxxxxxxxxxxxxxxxxxxxxxxxxxxxxxxxxxxxxxxxxxxxxxxxxxxxxxxxxxxxxxxxxxxxxxxxxxxxxxxxxxxxxxxxxxxxxxxxxxxxxxxxxxxxxxxxxxxxxxxxxxxxxxxxxxxxxxxxxxxxxxxxxxxxxxxxxxxxxxxxxxxxxxxxxxxxxxxxxxxxxxxxx 8
b11110 6
b101 ;
b100 :
1"
#8
bx 0
bx 1
bx B
bx A
bx @
bx ?
b11110 2
b11110 >
b101 :
0"
#10
b11 9
1"
#12
b101 :
0"
#14
b100 9
1"
#16
b101 :
0"
#18
b101 9
1"
#20
b1000110010111110 0
b11011111 1
b1111110 B
b1100101 A
b100011 @
b1100001 ?
b10 2
b10 >
b101 :
0"
#22
b110 9
bx0001000011xxxxxxxxxx00010xxxxxxxxxxxxxxxxxxxxxxxxxxxxxxxxxxxxxxxxxxxxxxxxxxxxxxxxxxxxxxxxxxxxxxxxxxxxxxxxxxxxxxxxxxxxxxxxxxxx '
bx0001000011xxxxxxxxxx00010xxxxxxxxxxxxxxxxxxxxxxxxxxxxxxxxxxxxxxxxxxxxxxxxxxxxxxxxxxxxxxxxxxxxxxxxxxxxxxxxxxxxxxxxxxxxxxxxxxxx 7
b1111100100000010000011111001001111111111111111111111111111111111111111111111111111111111111111111111111111111111111111111111111111 4
b110000000000000000000000 3
b11 <
b101111011110111100001011110111101111000001000110010111110xxxxxxxxxxxxxxxxxxxxxxxxxxxxxxxxxxxxxxxxxxxxxxxxxxxxxxxxxxxxxxxxxxxxxxxxxxxxxxxxxxxxxxxxxxxxxxxxxxxxxxxxxxxxxxxxxxxxxxxxxxxxxxxxxxxxxxxxxxxxxxxxxxxxxxxxxxxxxxxxxxxxxxxxxxxxxxxxxxxxxxxxxxxxxxxxxxxxxxxxxxxxxxxxxxxxxxxxxxxxxxxxxxxxxxxxxxxxxxxxxxxxxxxxxxxxxxxxxxxxxxxxxxxxxxxxxxxxxxxxxxxxxxxxxxxxxxxxxxxxxxxxxxxxxxxxxxxxxxxxxxxxxxxxxxxxxxxxxxxxxxxxxxxxxxxxxxxxxxxxxxxxxxxxxxxxxxxxxxxxxxxxxxxxxxxxxxxxxxxxxxxxxxxxxxxxxxxxxxxxxxxxxxxxxxxxxxxxxxxxxxxxxxxxxxxxxxxxxxxxxxxxxxxxxxxxxxxxxxxxxxxxxxxxxxxxxxxxxxxxxxxxxxxxxxxxxxxxxxxxxxxxxxxxxxxxxxxxxxxxxxxxxxxxxxxxxxxxxxxxxxxxxxxxxxxxxxxxxxxxxxxxxxxxxxxxxxxxxxxxxxxxxxxxxxxxxxxxxxxxxxxxxxxxxxxxxxxxxxxxxxxxxxxxxxxxxxxxxxxxxxxxxxxxxxxxxxxxxxxxxxxxxxxxxxxxxxxxxxxxxxxxxxxxxxxxxxxxxxxxxxxxxxxxxxxxxxxxxxxxxxxxxxxxxxxxxxxxxxxxxxxxxxxxxxxxxxxxxxxxxxxxxxxxxxxxxxxxxxxxxxxxxxxxxxxxxxxxxxxxxxxxxxxxxxxxxxxxxxxxxxxxxxxxxxxxxxxxxxxxxxxxxxxxxxxxxxxxxxxxxxxxxxxxxxxxxxxxxxxxxxxxxxxxxxxxxxxxxxxxxxxxxxxxxxxxxxxxxxxxxxxxxxxxxxxxxxxxxxxxxxxx 8
b11110 6
b101 ;
b100 :
1"
#24
bx 0
bx 1
bx B
bx A
bx @
bx ?
b11110 2
b11110 >
b101 :
0"
#26
b111 9
1"
#28
b101 :
0"
#30
b1000 9
1"
#32
b101 :
0"
#34
b1001 9
1"
#36
b100110111110 0
b11111111 1
b1111110 B
b1101101 A
b1100010 @
b1100000 ?
b1 2
b1 >
b101 :
0"
#38
b1010 9
b10001000011xxxxxxxxxx00010xxxxxxxxxxxxxxxxxxxxxxxxxxxxxxxxxxx00001xxxxxxxxxxxxxxxxxxxxxxxxxxxxxxxxxxxxxxxxxxxxxxxxxxxxxxxxxxxx '
b10001000011xxxxxxxxxx00010xxxxxxxxxxxxxxxxxxxxxxxxxxxxxxxxxxx00001xxxxxxxxxxxxxxxxxxxxxxxxxxxxxxxxxxxxxxxxxxxxxxxxxxxxxxxxxxxx 7
b11100100000010000011111001001111111111111111111111111111111111100111111111111111111111111111111111111111111111111111111111111111 4
b1110000000000000000000000 3
b100 <
b10111101111011110000101111011110111100000100011001011111000000000100110111110xxxxxxxxxxxxxxxxxxxxxxxxxxxxxxxxxxxxxxxxxxxxxxxxxxxxxxxxxxxxxxxxxxxxxxxxxxxxxxxxxxxxxxxxxxxxxxxxxxxxxxxxxxxxxxxxxxxxxxxxxxxxxxxxxxxxxxxxxxxxxxxxxxxxxxxxxxxxxxxxxxxxxxxxxxxxxxxxxxxxxxxxxxxxxxxxxxxxxxxxxxxxxxxxxxxxxxxxxxxxxxxxxxxxxxxxxxxxxxxxxxxxxxxxxxxxxxxxxxxxxxxxxxxxxxxxxxxxxxxxxxxxxxxxxxxxxxxxxxxxxxxxxxxxxxxxxxxxxxxxxxxxxxxxxxxxxxxxxxxxxxxxxxxxxxxxxxxxxxxxxxxxxxxxxxxxxxxxxxxxxxxxxxxxxxxxxxxxxxxxxxxxxxxxxxxxxxxxxxxxxxxxxxxxxxxxxxxxxxxxxxxxxxxxxxxxxxxxxxxxxxxxxxxxxxxxxxxxxxxxxxxxxxxxxxxxxxxxxxxxxxxxxxxxxxxxxxxxxxxxxxxxxxxxxxxxxxxxxxxxxxxxxxxxxxxxxxxxxxxxxxxxxxxxxxxxxxxxxxxxxxxxxxxxxxxxxxxxxxxxxxxxxxxxxxxxxxxxxxxxxxxxxxxxxxxxxxxxxxxxxxxxxxxxxxxxxxxxxxxxxxxxxxxxxxxxxxxxxxxxxxxxxxxxxxxxxxxxxxxxxxxxxxxxxxxxxxxxxxxxxxxxxxxxxxxxxxxxxxxxxxxxxxxxxxxxxxxxxxxxxxxxxxxxxxxxxxxxxxxxxxxxxxxxxxxxxxxxxxxxxxxxxxxxxxxxxxxxxxxxxxxxxxxxxxxxxxxxxxxxxxxxxxxxxxxxxxxxxxxxxxxxxxxxxxxxxxxxxxxxxxxxxxxxxxxxxxxxxxxxxxxxxxxxxxxxxxxxxxxxxxxxxxxxxxxxxxxxxxxxxxxx 8
b11110 6
b101 ;
b100 :
1"
#40
b10111101111011110 0
b1111111 1
b1111110 A
b1111110 @
b100010 ?
b11 2
b11 >
b101 :
0"
#42
b1011 9
1"
#44
b10010010011011110 0
b11100111 1
b100110 A
b1001001 @
b1100010 ?
b101 2
b101 >
b101 :
0"
#46
b1100 9
b10001000011xxxxxxxxxx0001000101xxxxxxxxxx00101xxxxxxxxxxxxxxx00001xxxxxxxxxxxxxxxxxxxxxxxxxxxxxxxxxxxxxxxxxxxxxxxxxxxxxxxxxxxx '
b10001000011xxxxxxxxxx0001000101xxxxxxxxxx00101xxxxxxxxxxxxxxx00001xxxxxxxxxxxxxxxxxxxxxxxxxxxxxxxxxxxxxxxxxxxxxxxxxxxxxxxxxxxx 7
b11100100000010000011111001000010111111111110011011111111111111100111111111111111111111111111111111111111111111111111111111111111 4
b1110100000000000000000000 3
b101 <
b1011110111101111000010111101111011110000010001100101111100000000010011011111000010010010011011110xxxxxxxxxxxxxxxxxxxxxxxxxxxxxxxxxxxxxxxxxxxxxxxxxxxxxxxxxxxxxxxxxxxxxxxxxxxxxxxxxxxxxxxxxxxxxxxxxxxxxxxxxxxxxxxxxxxxxxxxxxxxxxxxxxxxxxxxxxxxxxxxxxxxxxxxxxxxxxxxxxxxxxxxxxxxxxxxxxxxxxxxxxxxxxxxxxxxxxxxxxxxxxxxxxxxxxxxxxxxxxxxxxxxxxxxxxxxxxxxxxxxxxxxxxxxxxxxxxxxxxxxxxxxxxxxxxxxxxxxxxxxxxxxxxxxxxxxxxxxxxxxxxxxxxxxxxxxxxxxxxxxxxxxxxxxxxxxxxxxxxxxxxxxxxxxxxxxxxxxxxxxxxxxxxxxxxxxxxxxxxxxxxxxxxxxxxxxxxxxxxxxxxxxxxxxxxxxxxxxxxxxxxxxxxxxxxxxxxxxxxxxxxxxxxxxxxxxxxxxxxxxxxxxxxxxxxxxxxxxxxxxxxxxxxxxxxxxxxxxxxxxxxxxxxxxxxxxxxxxxxxxxxxxxxxxxxxxxxxxxxxxxxxxxxxxxxxxxxxxxxxxxxxxxxxxxxxxxxxxxxxxxxxxxxxxxxxxxxxxxxxxxxxxxxxxxxxxxxxxxxxxxxxxxxxxxxxxxxxxxxxxxxxxxxxxxxxxxxxxxxxxxxxxxxxxxxxxxxxxxxxxxxxxxxxxxxxxxxxxxxxxxxxxxxxxxxxxxxxxxxxxxxxxxxxxxxxxxxxxxxxxxxxxxxxxxxxxxxxxxxxxxxxxxxxxxxxxxxxxxxxxxxxxxxxxxxxxxxxxxxxxxxxxxxxxxxxxxxxxxxxxxxxxxxxxxxxxxxxxxxxxxxxxxxxxxxxxxxxxxxxxxxxxxxxxxxxxxxxxxxxxxxxxxxxxxxxxxxxxxxxxxxxxxxxxxxxxxxxxxxxx 8
b11110 6
b101 ;
b100 :
1"
#48
bx 0
bx 1
bx B
bx A
bx @
bx ?
b11110 2
b11110 >
b101 :
0"
#50
b1101 9
1"
#52
b1111101111011110 0
b11111111 1
b1111110 B
b1111110 A
b1111110 @
b1100001 ?
b0 2
b0 >
b101 :
0"
#54
b1110 9
b11110100000000000000000000 3
b110 <
b101111011110111100001011110111101111000001000110010111110000000001001101111100001001001001101111000001111101111011110xxxxxxxxxxxxxxxxxxxxxxxxxxxxxxxxxxxxxxxxxxxxxxxxxxxxxxxxxxxxxxxxxxxxxxxxxxxxxxxxxxxxxxxxxxxxxxxxxxxxxxxxxxxxxxxxxxxxxxxxxxxxxxxxxxxxxxxxxxxxxxxxxxxxxxxxxxxxxxxxxxxxxxxxxxxxxxxxxxxxxxxxxxxxxxxxxxxxxxxxxxxxxxxxxxxxxxxxxxxxxxxxxxxxxxxxxxxxxxxxxxxxxxxxxxxxxxxxxxxxxxxxxxxxxxxxxxxxxxxxxxxxxxxxxxxxxxxxxxxxxxxxxxxxxxxxxxxxxxxxxxxxxxxxxxxxxxxxxxxxxxxxxxxxxxxxxxxxxxxxxxxxxxxxxxxxxxxxxxxxxxxxxxxxxxxxxxxxxxxxxxxxxxxxxxxxxxxxxxxxxxxxxxxxxxxxxxxxxxxxxxxxxxxxxxxxxxxxxxxxxxxxxxxxxxxxxxxxxxxxxxxxxxxxxxxxxxxxxxxxxxxxxxxxxxxxxxxxxxxxxxxxxxxxxxxxxxxxxxxxxxxxxxxxxxxxxxxxxxxxxxxxxxxxxxxxxxxxxxxxxxxxxxxxxxxxxxxxxxxxxxxxxxxxxxxxxxxxxxxxxxxxxxxxxxxxxxxxxxxxxxxxxxxxxxxxxxxxxxxxxxxxxxxxxxxxxxxxxxxxxxxxxxxxxxxxxxxxxxxxxxxxxxxxxxxxxxxxxxxxxxxxxxxxxxxxxxxxxxxxxxxxxxxxxxxxxxxxxxxxxxxxxxxxxxxxxxxxxxxxxxxxxxxxxxxxxxxxxxxxxxxxxxxxxxxxxxxxxxxxxxxxxxxxxxxxxxxxxxxxxxxxxxxxxxxxxxxxxxxxxxxxxxxxxxxxxxxxxxxxxxxxxxxxxxxxxxxxxxxxxxxx 8
b11110 6
b101 ;
b100 :
1"
#56
b1000110010111110 0
b11011111 1
b1100101 A
b100011 @
b10 2
b10 >
b101 :
0"
#58
b1111 9
1"
#60
b1100100100000111110 0
b1101111 1
b1100001 A
b1010010 @
b101100 ?
b1101 2
b1101 >
b101 :
0"
#62
b10000 9
b10001000011xxxxxxxxxx0001000101xxxxxxxxxx00101xxxxxxxxxx0110100001xxxxxxxxxxxxxxxxxxxx01101xxxxxxxxxxxxxxxxxxxxxxxxxxxxxxxxxxx '
b10001000011xxxxxxxxxx0001000101xxxxxxxxxx00101xxxxxxxxxx0110100001xxxxxxxxxxxxxxxxxxxx01101xxxxxxxxxxxxxxxxxxxxxxxxxxxxxxxxxxx 7
b11100100000010000011111001000010111111111110011011111111110100000111111111111111111111110100111111111111111111111111111111111111 4
b11110100000001000000000000 3
b111 <
b10111101111011110000101111011110111100000100011001011111000000000100110111110000100100100110111100000111110111101111001100100100000111110xxxxxxxxxxxxxxxxxxxxxxxxxxxxxxxxxxxxxxxxxxxxxxxxxxxxxxxxxxxxxxxxxxxxxxxxxxxxxxxxxxxxxxxxxxxxxxxxxxxxxxxxxxxxxxxxxxxxxxxxxxxxxxxxxxxxxxxxxxxxxxxxxxxxxxxxxxxxxxxxxxxxxxxxxxxxxxxxxxxxxxxxxxxxxxxxxxxxxxxxxxxxxxxxxxxxxxxxxxxxxxxxxxxxxxxxxxxxxxxxxxxxxxxxxxxxxxxxxxxxxxxxxxxxxxxxxxxxxxxxxxxxxxxxxxxxxxxxxxxxxxxxxxxxxxxxxxxxxxxxxxxxxxxxxxxxxxxxxxxxxxxxxxxxxxxxxxxxxxxxxxxxxxxxxxxxxxxxxxxxxxxxxxxxxxxxxxxxxxxxxxxxxxxxxxxxxxxxxxxxxxxxxxxxxxxxxxxxxxxxxxxxxxxxxxxxxxxxxxxxxxxxxxxxxxxxxxxxxxxxxxxxxxxxxxxxxxxxxxxxxxxxxxxxxxxxxxxxxxxxxxxxxxxxxxxxxxxxxxxxxxxxxxxxxxxxxxxxxxxxxxxxxxxxxxxxxxxxxxxxxxxxxxxxxxxxxxxxxxxxxxxxxxxxxxxxxxxxxxxxxxxxxxxxxxxxxxxxxxxxxxxxxxxxxxxxxxxxxxxxxxxxxxxxxxxxxxxxxxxxxxxxxxxxxxxxxxxxxxxxxxxxxxxxxxxxxxxxxxxxxxxxxxxxxxxxxxxxxxxxxxxxxxxxxxxxxxxxxxxxxxxxxxxxxxxxxxxxxxxxxxxxxxxxxxxxxxxxxxxxxxxxxxxxxxxxxxxxxxxxxxxxxxxxxxxxxxxxxxxxxxxxxxxxxxxxxxxxxxxxxxxxxxxxxxxxxxxxxxxxxxxx 8
b11110 6
b101 ;
b100 :
1"
#64
bx 0
bx 1
bx B
bx A
bx @
bx ?
b11110 2
b11110 >
b101 :
0"
#66
b10001 9
1"
#68
b1000110010111110 0
b11011111 1
b1111110 B
b1100101 A
b100011 @
b1100001 ?
b10 2
b10 >
b101 :
0"
#70
b10010 9
1"
#72
b1000011110010111110 0
b1011011 1
b1000101 A
b101111 @
b101000 ?
b1001 2
b1001 >
b101 :
0"
